json_checker/__init__.py
json_checker/json_checker.py
json_checker/test.py
tests/__init__.py
tests/test_type_checker.py
JsonChecker_Svtter-0.0.1.dist-info/LICENSE
JsonChecker_Svtter-0.0.1.dist-info/METADATA
JsonChecker_Svtter-0.0.1.dist-info/WHEEL
JsonChecker_Svtter-0.0.1.dist-info/top_level.txt
JsonChecker_Svtter-0.0.1.dist-info/RECORD
