Metadata-Version: 2.1
Name: JsonChecker-Svtter
Version: 0.0.1
Summary: Check the python dict type via json file.
Home-page: https://github.com/Svtter/JsonChecker
Author: Svtter
Author-email: svtter@qq.com
License: UNKNOWN
Platform: UNKNOWN
Classifier: Programming Language :: Python :: 3
Classifier: License :: OSI Approved :: MIT License
Classifier: Operating System :: OS Independent
Requires-Python: >=3.7
